Workbook

Sheet Cover
D12: Compact Valuation Model | N12: Strictly Confidential
D14: Table of Contents | N14: Model Check
D16: Outputs | M16: Balance Sheet Balanced? | N16: =IF(SUM(Model!$J$106:$M$106)=0,1,0) -> 1
D17: Inputs
D18: Model
D32: © 2015 to 2023 CFI Education Inc.
D33: This Excel model is for educational purposes only and should not be used for any other reason. All content is Copyright material of CFI Education Inc.
D34: All rights reserved. The contents of this publication, including but not limited to all written material, content layout, images, formulas, and code, are protected
D35: under international copyright and trademark laws. No part of this publication may be modified, manipulated, reproduced, distributed, or transmitted in any
D36: form by any means, including photocopying, recording, or other electronic or mechanical methods, without prior written permission of the publisher,
D37: except in the case of certain noncommercial uses permitted by copyright law.
D39: https://corporatefinanceinstitute.com/

Sheet Outputs
B5: Sensitivity Analysis
B7: All figures in USD thousands unless stated
D10: Terminal Growth Rate | G10: 0.02 | L10: Shares Outstanding | N10: (FD 000) | O10: 34200
D11: WACC 1 | G11: 0.135 | L11: Current Price | N11: ($/sh) | O11: 2.71
D12: Enterprise Value | G12: =Model!G140 -> 284580.33
D13: Net Debt | G13: =-Model!G141 -> 21000
D17: ENTERPRISE VALUE 2 | L17: EQUITY VALUE PER SHARE
D19: Terminal Growth Rate | L19: Terminal Growth Rate
C20: =G12 -> 284580.33 | D20: =E20-0.005 -> 0.01 | E20: =F20-0.005 -> 0.015 | F20: =G10 -> 0.02 | G20: =F20+0.005 -> 0.025 | H20: =G20+0.005 -> 0.03 | L20: =D20 -> 0.01 | M20: =E20 -> 0.015 | N20: =F20 -> 0.02 | O20: =G20 -> 0.025 | P20: =H20 -> 0.03
B21: WACC | C21: =C22-0.005 -> 0.125 | D21: 283710.68 | E21: 273411.77 | F21: 273411.77 | G21: 283710.68 | H21: 307251.05 | J21: WACC | K21: =C21 -> 0.125 | L21: =D33/$O$10 -> 7.6815989 | M21: =E33/$O$10 -> 7.380461 | N21: =F33/$O$10 -> 7.380461 | O21: =G33/$O$10 -> 7.6815989 | P21: =H33/$O$10 -> 8.3699138
C22: =C23-0.005 -> 0.13 | D22: 294479.23 | E22: 283302.94 | F22: 283302.94 | G22: 294479.23 | H22: 320184.68 | K22: =C22 -> 0.13 | L22: =D34/$O$10 -> 7.9964686 | M22: =E34/$O$10 -> 7.6696767 | N22: =F34/$O$10 -> 7.6696767 | O22: =G34/$O$10 -> 7.9964686 | P22: =H34/$O$10 -> 8.7480901
C23: =G11 -> 0.135 | D23: 294479.23 | E23: 283302.94 | F23: 283302.94 | G23: 294479.23 | H23: 320184.68 | K23: =C23 -> 0.135 | L23: =D35/$O$10 -> 7.9964686 | M23: =E35/$O$10 -> 7.6696767 | N23: =F35/$O$10 -> 7.6696767 | O23: =G35/$O$10 -> 7.9964686 | P23: =H35/$O$10 -> 8.7480901
C24: =C23+0.005 -> 0.14 | D24: 283710.68 | E24: 273411.77 | F24: 273411.77 | G24: 283710.68 | H24: 307251.05 | K24: =C24 -> 0.14 | L24: =D36/$O$10 -> 7.6815989 | M24: =E36/$O$10 -> 7.380461 | N24: =F36/$O$10 -> 7.380461 | O24: =G36/$O$10 -> 7.6815989 | P24: =H36/$O$10 -> 8.3699138
C25: =C24+0.005 -> 0.145 | D25: 264599.11 | E25: 255761.27 | F25: 255761.27 | G25: 264599.11 | H25: 284580.33 | K25: =C25 -> 0.145 | L25: =D37/$O$10 -> 7.1227811 | M25: =E37/$O$10 -> 6.8643645 | N25: =F37/$O$10 -> 6.8643645 | O25: =G37/$O$10 -> 7.1227811 | P25: =H37/$O$10 -> 7.7070272
D29: EQUITY VALUE | L29: PREMIUM (DISCOUNT) TO CURRENT PRICE
D31: Terminal Growth Rate | L31: Terminal Growth Rate
D32: =D20 -> 0.01 | E32: =E20 -> 0.015 | F32: =F20 -> 0.02 | G32: =G20 -> 0.025 | H32: =H20 -> 0.03 | L32: =D20 -> 0.01 | M32: =E20 -> 0.015 | N32: =F20 -> 0.02 | O32: =G20 -> 0.025 | P32: =H20 -> 0.03
B33: WACC | C33: =C21 -> 0.125 | D33: =D21-$G$13 -> 262710.68 | E33: =E21-$G$13 -> 252411.77 | F33: =F21-$G$13 -> 252411.77 | G33: =G21-$G$13 -> 262710.68 | H33: =H21-$G$13 -> 286251.05 | K33: =C21 -> 0.125 | L33: =L21/$O$11-1 -> 1.8345383 | M33: =M21/$O$11-1 -> 1.7234174 | N33: =N21/$O$11-1 -> 1.7234174 | O33: =O21/$O$11-1 -> 1.8345383 | P33: =P21/$O$11-1 -> 2.0885291
C34: =C22 -> 0.13 | D34: =D22-$G$13 -> 273479.23 | E34: =E22-$G$13 -> 262302.94 | F34: =F22-$G$13 -> 262302.94 | G34: =G22-$G$13 -> 273479.23 | H34: =H22-$G$13 -> 299184.68 | K34: =C22 -> 0.13 | L34: =L22/$O$11-1 -> 1.9507264 | M34: =M22/$O$11-1 -> 1.830139 | N34: =N22/$O$11-1 -> 1.830139 | O34: =O22/$O$11-1 -> 1.9507264 | P34: =P22/$O$11-1 -> 2.2280775
C35: =C23 -> 0.135 | D35: =D23-$G$13 -> 273479.23 | E35: =E23-$G$13 -> 262302.94 | F35: =F23-$G$13 -> 262302.94 | G35: =G23-$G$13 -> 273479.23 | H35: =H23-$G$13 -> 299184.68 | K35: =C23 -> 0.135 | L35: =L23/$O$11-1 -> 1.9507264 | M35: =M23/$O$11-1 -> 1.830139 | N35: =N23/$O$11-1 -> 1.830139 | O35: =O23/$O$11-1 -> 1.9507264 | P35: =P23/$O$11-1 -> 2.2280775
C36: =C24 -> 0.14 | D36: =D24-$G$13 -> 262710.68 | E36: =E24-$G$13 -> 252411.77 | F36: =F24-$G$13 -> 252411.77 | G36: =G24-$G$13 -> 262710.68 | H36: =H24-$G$13 -> 286251.05 | K36: =C24 -> 0.14 | L36: =L24/$O$11-1 -> 1.8345383 | M36: =M24/$O$11-1 -> 1.7234174 | N36: =N24/$O$11-1 -> 1.7234174 | O36: =O24/$O$11-1 -> 1.8345383 | P36: =P24/$O$11-1 -> 2.0885291
C37: =C25 -> 0.145 | D37: =D25-$G$13 -> 243599.11 | E37: =E25-$G$13 -> 234761.27 | F37: =F25-$G$13 -> 234761.27 | G37: =G25-$G$13 -> 243599.11 | H37: =H25-$G$13 -> 263580.33 | K37: =C25 -> 0.145 | L37: =L25/$O$11-1 -> 1.6283325 | M37: =M25/$O$11-1 -> 1.5329758 | N37: =N25/$O$11-1 -> 1.5329758 | O37: =O25/$O$11-1 -> 1.6283325 | P37: =P25/$O$11-1 -> 1.8439215
P40: WACC = Weighted Average Cost of Capital.
P41: This table requires the workbook calculation to be set to automatic to update.

Sheet Inputs
B5: Model Assumptions
B7: All figures in USD thousands unless stated | H7: =I7-1 -> 2020 | I7: =J7-1 -> 2021 | J7: =K7-1 -> 2022 | K7: 2023 | L7: =K7+1 -> 2024 | M7: =L7+1 -> 2025 | N7: =M7+1 -> 2026 | O7: =N7+1 -> 2027
C9: INCOME STATEMENT
C11: Revenue | H11: 45201 | I11: 50164 | J11: 54261 | K11: 58000 | L11: 61500 | M11: 64500 | N11: 68000 | O11: 71500 | T11: Revenue | U11: 60000
C12: COGS | H12: 24518 | I12: 26589 | J12: 28541 | K12: 30000 | L12: 31000 | M12: 32000 | N12: =34000 -> 34000 | O12: 36000 | T12: COGS | U12: 30500
C13: SG&A | H13: 4800 | I13: 5100 | J13: 5500 | K13: 6000 | L13: 6600 | M13: 7300 | N13: 7700 | O13: 8100 | T13: SG&A | U13: 6250
C14: Other Expenses | H14: 1987 | I14: 2016 | J14: 2045 | K14: 2000 | L14: 2000 | M14: 2000 | N14: 2000 | O14: -2000
C15: Depreciation | H15: 3985 | I15: 4005 | J15: 4058 | K15: =4000 -> 4000 | L15: =4000 -> 4000 | M15: =4000 -> 4000 | N15: =4000 -> 4000 | O15: =4000 -> 4000
C16: Interest Expense | H16: 1845 | I16: 1652 | J16: 1398 | K16: 1200 | L16: 1000 | M16: 800 | N16: 600 | O16: 400
C17: Current Tax (Levered) 1 | H17: 987 | I17: 992 | J17: 1000 | K17: 1000 | L17: 1000 | M17: 1000 | N17: 1000 | O17: 1000
C18: Deferred Tax (Levered) 1 | H18: 1957 | I18: 2001 | J18: 2006 | K18: 2000 | L18: 2000 | M18: 2000 | N18: 20000 | O18: 2000
C21: CASH FLOW STATEMENT
C23: Cash From Operations
C24: Cash from Accounts Receivable | H24: 27 | I24: 35 | J24: 31 | K24: 30 | L24: 30 | M24: 30 | N24: 30 | O24: 30
C25: Cash from Inventory | H25: -185 | I25: -203 | J25: -220 | K25: -200 | L25: -200 | M25: -200 | N25: -200 | O25: -200
C26: Cash from Accounts Payable | H26: 168 | I26: 182 | J26: 174 | K26: 175 | L26: 175 | M26: 175 | N26: 175 | O26: 175
C28: Cash From Investing
C29: Capital Expenditure | H29: -3997 | I29: -4016 | J29: -4002 | K29: -4000 | L29: -4000 | M29: -4000 | N29: -4000 | O29: -4000
C31: Cash From Financing
C32: Line of Credit Issue / (Repay) | H32: -587 | I32: -875 | J32: -994 | K32: -7000 | L32: 0 | M32: 0 | N32: 0 | O32: 0
C33: Term Loan Issue / (Repay) | H33: -3000 | I33: -3000 | J33: -3000 | K33: -3000 | L33: -3000 | M33: -3000 | N33: -3000 | O33: -3000
C34: Equity Issue / (Buyback) | H34: 0 | I34: 0 | J34: 0 | K34: -500 | L34: -500 | M34: -500 | N34: -500 | O34: -500
C35: Payment of Dividends | H35: -1000 | I35: -1000 | J35: -1000 | K35: -1000 | L35: -1000 | M35: -1000 | N35: -1000 | O35: 1000
C38: UNLEVERED FREE CASH FLOW
C40: Current Tax (Unlevered) 2 | H40: 1086 | I40: 1091 | J40: 1104 | K40: 1100 | L40: 1100 | M40: 1100 | N40: 1100 | O40: 1100
O43: These are levered taxes calculated after the impact of interest expense.
O44: These are unlevered taxes calculated before the impact of interest expense.

Sheet Model
B5: Income Statement
B7: All figures in USD thousands unless stated | K7: =Inputs!K7 -> 2023 | L7: =Inputs!L7 -> 2024 | M7: =Inputs!M7 -> 2025 | N7: =Inputs!N7 -> 2026 | O7: =Inputs!O7 -> 2027
C10: Revenue | K10: =Inputs!K11 -> 58000 | L10: =Inputs!L11 -> 61500 | M10: =Inputs!M11 -> 64500 | N10: 68000 | O10: =Inputs!O11 -> 71500
C11: COGS | K11: =-Inputs!K12 -> -30000 | L11: =-Inputs!L12 -> -31000 | M11: =-Inputs!M12 -> -32000 | N11: =-Inputs!N12 -> -34000 | O11: =-Inputs!O12 -> -36000
C12: Gross Profit | K12: =SUM(K10:K11) -> 28000 | L12: =SUM(L10:L11) -> 30500 | M12: =SUM(M10:M11) -> 32500 | N12: =SUM(N10:N11) -> 34000 | O12: =SUM(O10:O11) -> 35500
C15: SG&A | K15: =-Inputs!J13 -> -5500 | L15: =-Inputs!K13 -> -6000 | M15: =-Inputs!L13 -> -6600 | N15: =-Inputs!M13 -> -7300 | O15: =-Inputs!N13 -> -7700
C16: Other | K16: =-Inputs!K14 -> -2000 | L16: =-Inputs!L14-200 -> -2200 | M16: =-Inputs!M14 -> -2000 | N16: =-Inputs!N14 -> -2000 | O16: =-Inputs!O14 -> 2000
C17: EBITDA | K17: =K12+SUM(K15:K16) -> 20500 | L17: =L12+SUM(L15:L16) -> 22300 | M17: =M12+SUM(M15:M16) -> 23900 | N17: =N12+SUM(N15:N16) -> 24700 | O17: =O12+SUM(O15:O16) -> 29800
C20: Depreciation | K20: =-Inputs!K15 -> -4000 | L20: =-Inputs!L15 -> -4000 | M20: =-Inputs!M15 -> -4000 | N20: =-Inputs!N15 -> -4000 | O20: =-Inputs!O15 -> -4000
C21: EBIT | K21: =K20+K17 -> 16500 | L21: =L20+L17 -> 18300 | M21: =M20+M17 -> 19900 | N21: =N20+N17 -> 20700 | O21: =O20+O17 -> 25800
C24: Interest Expense | K24: =-Inputs!K16 -> -1200 | L24: =-Inputs!L16 -> -1000 | M24: =-Inputs!M16 -> -800 | N24: =-600 -> -600 | O24: =-Inputs!O16 -> -400
C25: EBT | K25: =K24+K21 -> 15300 | L25: =L24+L21 -> 17300 | M25: =M24+M21 -> 19100 | N25: =N24+N21 -> 20100 | O25: =O24+O21 -> 25400
C28: Current Tax | K28: =-Inputs!J17 -> -1000 | L28: =-Inputs!K17 -> -1000 | M28: =-Inputs!L17 -> -1000 | N28: =-Inputs!M17 -> -1000 | O28: =-Inputs!N17 -> -1000
C29: Deferred Tax | K29: =-Inputs!K18 -> -2000 | L29: =-Inputs!K18 -> -2000 | M29: =-Inputs!M18 -> -2000 | N29: =-Inputs!N18 -> -20000 | O29: =-Inputs!O18 -> -2000
C30: Total Tax 1 | K30: =SUM(K28:K29) -> -3000 | L30: =SUM(L28:L29) -> -3000 | M30: =SUM(M28:M29) -> -3000 | N30: =SUM(N28:N29) -> -21000 | O30: =SUM(O28:O29) -> -3000
C33: Net Income | K33: =K25-K30 -> 18300 | L33: =L25-L30 -> 20300 | M33: =M25-M30 -> 22100 | N33: =N25-N30 -> 41100 | O33: =O25-O30 -> 28400
O36: These are levered taxes calculated after the impact of interest expense.
B40: Cash Flow Statement
B42: All figures in USD thousands unless stated | K42: =K$7 -> 2023 | L42: =L$7 -> 2024 | M42: =M$7 -> 2025 | N42: =N$7 -> 2026 | O42: =O$7 -> 2027
C45: CASH FROM OPERATIONS
C46: Net Income | K46: =K33 -> 18300 | L46: =L33 -> 20300 | M46: =M33 -> 22100 | N46: =N33 -> 41100 | O46: =O33 -> 28400
C47: Depreciation | K47: =-K20 -> 4000 | L47: =-L20 -> 4000 | M47: =-M20 -> 4000 | N47: =-N20 -> 4000 | O47: =-O20 -> 4000
C48: Deferred Tax | K48: =-L29 -> 2000 | L48: =-M29 -> 2000 | M48: =-N29 -> 20000 | N48: =-O29 -> 2000 | O48: =-P29 -> 0
C49: Cash from Accounts Receivable | K49: =Inputs!K24 -> 30 | L49: =Inputs!L24 -> 30 | M49: =Inputs!M24 -> 30 | N49: =Inputs!N24 -> 30 | O49: =Inputs!O24 -> 30
C50: Cash from Inventory | K50: =Inputs!K25 -> -200 | L50: =Inputs!L25 -> -200 | M50: =Inputs!M25 -> -200 | N50: =Inputs!N25 -> -200 | O50: =Inputs!O25 -> -200
C51: Cash from Accounts Payable | K51: =Inputs!K26 -> 175 | L51: =Inputs!L26 -> 175 | M51: =Inputs!M26 -> 175 | N51: =Inputs!N26 -> 175 | O51: =Inputs!O26 -> 175
C52: Subtotal | K52: =SUM(K46:K51) -> 24305 | L52: =SUM(L46:L51) -> 26305 | M52: =SUM(M46:M51) -> 46105 | N52: =SUM(N46:N51) -> 47105 | O52: =SUM(O46:O51) -> 32405
C55: CASH FROM INVESTING
C56: Capital Expenditure | K56: =-Inputs!K29 -> 4000 | L56: =-Inputs!L29 -> 4000 | M56: =-Inputs!M29 -> 4000 | N56: =-Inputs!N29 -> 4000 | O56: =-Inputs!O29 -> 4000
C57: Subtotal | K57: =SUM(K56) -> 4000 | L57: =SUM(L56) -> 4000 | M57: =SUM(M56) -> 4000 | N57: =SUM(N56) -> 4000 | O57: =SUM(O56) -> 4000
C60: CASH FROM FINANCING
C61: Line of Credit Issue / (Repay) | K61: =Inputs!K32 -> -7000 | L61: =Inputs!L32 -> 0 | M61: =Inputs!M32 -> 0 | N61: =Inputs!N32 -> 0 | O61: =Inputs!O32 -> 0
C62: Term Loan Issue / (Repay) | K62: =Inputs!K33 -> -3000 | L62: =Inputs!L33 -> -3000 | M62: =Inputs!M33 -> -3000 | N62: =Inputs!N33 -> -3000 | O62: =Inputs!O33 -> -3000
C63: Equity Issue / (Buyback) | K63: =Inputs!K34 -> -500 | L63: =Inputs!L34 -> -500 | M63: =Inputs!M34 -> -500 | N63: =Inputs!N34 -> -500 | O63: =Inputs!O34 -> -500
C64: Payment of Dividends | K64: =Inputs!K35 -> -1000 | L64: =Inputs!L35 -> -1000 | M64: =Inputs!M35 -> -1000 | N64: =Inputs!N35 -> -1000 | O64: =Inputs!O35 -> 1000
C65: Subtotal | K65: =SUM(K62:K64) -> -4500 | L65: =SUM(L62:L64) -> -4500 | M65: =SUM(M62:M64) -> -4500 | N65: =SUM(N62:N64) -> -4500 | O65: =SUM(O62:O64) -> -2500
C68: CASH BALANCE
C69: Beginning | K69: =J81 -> 5000 | L69: =K81 -> 5000 | M69: =L81 -> 5000 | N69: =M81 -> 5000 | O69: =N81 -> 5000
C70: Change in Cash | K70: =K65+K57+K52 -> 23805 | L70: =L65+L57+L52 -> 25805 | M70: =M65+M57+M52 -> 45605 | N70: =N65+N57+N52 -> 46605 | O70: =O65+O57+O52 -> 33905
C71: Ending | K71: =SUM(K69:K70) -> 28805 | L71: =SUM(L69:L70) -> 30805 | M71: =SUM(M69:M70) -> 50605 | N71: =SUM(N69:N70) -> 51605 | O71: =SUM(O69:O70) -> 38905
B75: Balance Sheet
B77: All figures in USD thousands unless stated | J77: =K77-1 -> 2022 | K77: =K$7 -> 2023 | L77: =L$7 -> 2024 | M77: =M$7 -> 2025 | N77: =N$7 -> 2026 | O77: =O$7 -> 2027
C80: ASSETS
C81: Cash | J81: 5000 | K81: =K69 -> 5000 | L81: =L69 -> 5000 | M81: =M69 -> 5000 | N81: =N69 -> 5000 | O81: =O69 -> 5000
C82: Accounts Receivable | J82: 6000 | K82: =J82-K49 -> 5970 | L82: =K82-L49 -> 5940 | M82: =L82-M49 -> 5910 | N82: =M82-N49 -> 5880 | O82: =N82-O49 -> 5850
C83: Inventory | J83: 2000 | K83: =J83-K50 -> 2200 | L83: =K83-L50 -> 2400 | M83: =L83-M50 -> 2600 | N83: 2800 | O83: =N83-O50 -> 3000
C84: Property Plant & Equipment | J84: 65000 | K84: =J84-K56-K47 -> 57000 | L84: =K84-L56-L47 -> 49000 | M84: =L84-M56-M47 -> 41000 | N84: =M84-N56-N47 -> 33000 | O84: =N84-O56-O47 -> 25000
C85: Total Assets | J85: =SUM(J81:J84) -> 78000 | K85: =SUM(K81:K84) -> 70170 | L85: =SUM(L81:L84) -> 62340 | M85: =SUM(M81:M84) -> 54510 | N85: =SUM(N81:N84) -> 46680 | O85: =SUM(O81:O84) -> 38850
C89: LIABILITIES
C90: Accounts Payable | J90: 3000 | K90: =J90+L51 -> 3175 | L90: =K90+M51 -> 3350 | M90: =L90+N51 -> 3525 | N90: =M90+O51 -> 3700 | O90: =N90+P51 -> 3700
C91: Line of Credit | J91: 7000 | K91: =J91+K61 -> 0 | L91: =K91+L61 -> 0 | M91: =L91+M61 -> 0 | N91: =M91+N61 -> 0 | O91: =N91+O61 -> 0
C92: Term Loan | J92: 20000 | K92: =J92+K62 -> 17000 | L92: =K92+L62 -> 14000 | M92: =L92+M62 -> 11000 | N92: =M92+N62 -> 8000 | O92: =N92+O62 -> 5000
C93: Deferred Taxes | J93: 1000 | K93: =J93+K48 -> 3000 | L93: =K93+L48 -> 5000 | M93: =L93+M48 -> 25000 | N93: =M93+N48 -> 27000 | O93: =N93+O48 -> 27000
C94: Total Liabilities | J94: =SUM(J90:J93) -> 31000 | K94: =SUM(K91:K93) -> 20000 | L94: =SUM(L91:L93) -> 19000 | M94: =SUM(M91:M93) -> 36000 | N94: =SUM(N91:N93) -> 35000 | O94: =SUM(O91:O93) -> 32000
C98: EQUITY
C99: Equity Capital | J99: 42000 | K99: =J99+K63-700 -> 40800 | L99: =K99+L63 -> 40300 | M99: =L99+M63 -> 39800 | N99: =M99+N63 -> 39300 | O99: =N99+O63 -> 38800
C100: Retained Earnings | J100: 5000 | K100: =K85-K94-K99 -> 9370 | L100: =L85-L94-L99 -> 3040 | M100: =M85-M94-M99 -> -21290 | N100: =N85-N94-N99 -> -27620 | O100: =O85-O94-O99 -> -31950
C101: Shareholders' Equity | J101: =SUM(J99:J100) -> 47000 | K101: =SUM(K99:K100) -> 50170 | L101: =SUM(L99:L100) -> 43340 | M101: =SUM(M99:M100) -> 18510 | N101: =SUM(N99:N100) -> 11680 | O101: =SUM(O99:O100) -> 6850
C103: Total Liabilities & Equity | J103: =J101+J94 -> 78000 | K103: =K101+K94 -> 70170 | L103: =L101+L94 -> 62340 | M103: =M101+M94 -> 54510 | N103: =N101+N94 -> 46680 | O103: =O101+O94 -> 38850
C106: Check | J106: =J85-J103 -> 0 | K106: =K85-K103 -> 0 | L106: =L85-L103 -> 0 | M106: =M85-M103 -> 0 | N106: =N85-N103 -> 0 | O106: =O85-O103 -> 0
B110: Discounted Cash Flow Schedule
B112: All figures in USD thousands unless stated | J112: Valuation | K112: Discrete Forecast | P112: Term
J113: (YY-MM-DD) | K113: (YY-MM-DD) | L113: (YY-MM-DD) | M113: (YY-MM-DD) | N113: (YY-MM-DD) | O113: (YY-MM-DD) | P113: (YY-MM-DD)
J114: =DATE(G126,1,1) -> 44927 | K114: =DATE(G126,12,31) -> 45291 | L114: =EDATE(K114,12) -> 45657 | M114: =EDATE(L114,12) -> 46022 | N114: =EDATE(M114,12) -> 46387 | O114: =EDATE(N114,12) -> 46752 | P114: =EDATE(O114,12) -> 47118
C116: UNLEVERED FREE CASH FLOW
C117: EBITDA 1 | K117: =K17 -> 20500 | L117: =L17 -> 22300 | M117: =M17 -> 23900 | N117: =N17 -> 24700 | O117: =O17 -> 29800 | P117: =O117*(1+G127) -> 30396
C118: Current Taxes (Unlevered) 2 | K118: =-Inputs!K40 -> -1100 | L118: =-Inputs!L40 -> -1100 | M118: =-Inputs!M40 -> -1100 | N118: =-Inputs!N40 -> -1100 | O118: =-Inputs!O40 -> -1100 | P118: =O118 -> -1100
C119: Capital Expenditure 2 | K119: =-K56 -> -4000 | L119: =-L56 -> -4000 | M119: =-M56 -> -4000 | N119: =-N56 -> -4000 | O119: =-O56 -> -4000 | P119: =O119 -> -4000
C120: Cash from Working Capital 3 | K120: =SUM(K50:K51) -> -25 | L120: =SUM(L50:L51) -> -25 | M120: =SUM(M50:M51) -> -25 | N120: =SUM(N50:N51) -> -25 | O120: =SUM(O50:O51) -> -25 | P120: 0
C121: Unlevered Free Cash Flow | K121: =SUM(K117:K120) -> 15375 | L121: =SUM(L117:L120) -> 17175 | M121: =SUM(M117:M120) -> 18775 | N121: =SUM(N117:N120) -> 19575 | O121: =SUM(O117:O120) -> 24675 | P121: =SUM(P117:P120) -> 25296
D125: ASSUMPTIONS | K125: CASH FLOW PROFILES
D126: First Year of Forecast | G126: =K77 -> 2023 | I126: Discrete Forecast | K126: =K121 -> 15375 | L126: =L121 -> 17175 | M126: =M121 -> 18775 | N126: =N121 -> 19575 | O126: =O121 -> 24675
D127: Terminal Growth Rate | G127: =Outputs!G10 -> 0.02 | I127: Terminal Value 4 | K127: 0 | L127: 0 | M127: 0 | N127: 0 | O127: =P121/(G128-G127) -> 219965.22
D128: Weighted Avg. Cost of Capital | G128: =Outputs!G11 -> 0.135 | I128: Total Cash Flow | K128: =SUM(K126:K127) -> 15375 | L128: =SUM(L126:L127) -> 17175 | M128: =SUM(M126:M127) -> 18775 | N128: =SUM(N126:N127) -> 19575 | O128: =SUM(O126:O127) -> 244640.22
D132: ENTERPRISE VALUE | K132: EQUITY VALUE PER SHARE
D133: PV of Discrete | F133: =NPV(G128,K126:O126) -> 64615.113 | G133: =F133/$F$135 -> 0.22705404 | K133: Equity Value | N133: =G142 -> 263580.33
D134: PV of Terminal | F134: =NPV(G129,K127:O127) -> 219965.22 | G134: =F134/$F$135 -> 0.77294596 | K134: Shares Outstanding | M134: (FD 000) | N134: =Outputs!O10 -> 34200
D135: Enterprise Value | F135: =SUM(F133:F134) -> 284580.33 | G135: =F135/$F$135 -> 1 | K135: Equity Value | M135: (USD/sh) | N135: =N133/N134 -> 7.7070272
D139: EQUITY VALUE | K139: PREMIUM (DISCOUNT)
D140: Enterprise Value | G140: =F135 -> 284580.33 | K140: Equity Value | M140: (USD/sh) | N140: =N135 -> 7.7070272
D141: Less: Net Debt | G141: =-(J92+J91-J82) -> -21000 | K141: Current Price | M141: (USD/sh) | N141: =Outputs!O11 -> 2.71
D142: Equity Value | G142: =SUM(G140:G141) -> 263580.33 | K142: Premium (Discount) | N142: =N140/N141-1 -> 1.8439215
N145: Terminal year EBITDA is equal to previous year grown at the terminal growth rate.
N146: Current taxes & capital expenditure in terminal year have been set equal to the previous year.
N147: Cash from working capital has been set to zero in the terminal year.
N148: The growing perpetuity method was used to calculate the terminal value.

Sheet Hidden
B2: Forecasts | C2: 2023 | D2: =C2+1 -> 2024 | E2: =D2+1 -> 2025
B4: Revenue | C4: 60000 | D4: 62000 | E4: 63500
B5: COGS | C5: 30500 | D5: 31250 | E5: 32500
B6: SG&A | C6: 6250 | D6: 6850 | E6: 7000

Sheet Buried
B2: Income Statement | D2: 2023 | E2: =D2+1 -> 2024 | F2: =E2+1 -> 2025
B4: Revenue | D4: 58000 | E4: 61500 | F4: 64500
B5: COGS | D5: -30000 | E5: -31000 | F5: -32000
B6: Gross Profit | D6: =SUM(D4:D5) -> 28000 | E6: =SUM(E4:E5) -> 30500 | F6: =SUM(F4:F5) -> 32500
B9: SG&A | D9: -6000 | E9: -6600 | F9: -7300
B10: Other | D10: -2000 | E10: -2000 | F10: -2000
B11: EBITDA | D11: =D6+SUM(D9:D10) -> 20000 | E11: =E6+SUM(E9:E10) -> 21900 | F11: =F6+SUM(F9:F10) -> 23200
