Workbook

Sheet Dashboard
A1: Note to the Blyth user
A2: To whoever reading this as a template,
A4: * Please note that for each DCF that you do, the breakdown of the line-items on the financial statements will vary from company to company and ought to be customized accordingly.
A5: * Please consult SEC filings, Bloomberg, or Google/Yahoo! Finance to obtain financial statement data.
A6: * A rigorous DCF will further break down the conventional GAAP line items to incorporate even more granular assumptions. We strongly suggest that you do so.
A8: If you have any questions, please do not hesitate to contact a Director or your Portfolio Manager for help.
A10: Happy modeling,
A11: Andrew Han
A13: DCF Dashboard
A14: in $ mm's
A15: Source | B15: 2013 10K SEC Filing, Google Finance, and Bloomberg
A17: In blue are assumptions
A19: Company | B19: WebMD
A20: Ticker | B20: WBMD
A21: Current Price | B21: 48.35
A22: Terminal Growth Rate | B22: 0.02
A23: Market Risk Premium | B23: 0.06 | D23: NYU prof estimate. http://people.stern.nyu.edu/adamodar/
A24: Risk-Free Rate | B24: 0.023 | D24: 10-yr treasury. http://www.bloomberg.com/markets/rates-bonds/government-bonds/us/
A25: WACC | B25: ='FV Calculation'!B15 -> 0.057457938
A27: Fair Price | B27: ='FV Calculation'!$B$11/'FV Calculation'!$B$32 -> 44.049329
A28: Appreciation | B28: =(B27-B21)/B21 -> -0.088948726
A31: Thesis and Notes
A33: Thesis | B33: Patent cliff that is facing many pharmaceutical companies will cause them to slash marketing budgets, which poses a real threat to WebMD revenue.
A35: Notes | B35: This is where you would note important assumptions that you've included in your model

Sheet Income Statement
A1: Income Statement
A2: in mms | B2: Historical | F2: Projected
B3: 2010 | C3: 2011 | D3: 2012 | E3: 2013 | F3: 2014 | G3: 2015 | H3: 2016 | I3: 2017 | J3: 2018 | L3: Notes
L4: In blue are projections, highlighted in grey are assumptions
A6: Public Portal Advertising and Sponsorship | B6: 447 | C6: 477.3 | D6: 391.3 | E6: 433.2 | F6: =E6*(1+F7) -> 476.52 | G6: =F6*(1+G7) -> 524.172 | H6: =G6*(1+H7) -> 576.5892 | I6: =H6*(1+I7) -> 634.24812 | J6: =I6*(1+J7) -> 697.67293 | L6: These are WebMD specific revenue segments. Ideally you want to break it out for your company
A7: % change | C7: =(C6-B6)/B6 -> 0.067785235 | D7: =(D6-C6)/C6 -> -0.18018018 | E7: =(E6-D6)/D6 -> 0.10707897 | F7: 0.1 | G7: 0.1 | H7: 0.1 | I7: 0.1 | J7: 0.1
A8: Private Portal Services | B8: 87.6 | C8: 81.5 | D8: 78.5 | E8: 82.1 | F8: =E8*(1+F9) -> 86.205 | G8: =F8*(1+G9) -> 90.51525 | H8: =G8*(1+H9) -> 95.041013 | I8: =H8*(1+I9) -> 99.793063 | J8: =I8*(1+J9) -> 104.78272 | L8: This way it's a lot more granular than just projecting out total revenue
A9: % change | C9: =(C8-B8)/B8 -> -0.069634703 | D9: =(D8-C8)/C8 -> -0.036809816 | E9: =(E8-D8)/D8 -> 0.045859873 | F9: 0.05 | G9: 0.05 | H9: 0.05 | I9: 0.05 | J9: 0.05 | L9: I obviously didn't incorporate great assumptions (10% and 5%)
A10: Revenue | B10: =B6+B8 -> 534.6 | C10: 558.77 | D10: 469.87 | E10: 515.29 | F10: =F6+F8 -> 562.725 | G10: =G6+G8 -> 614.68725 | H10: =H6+H8 -> 671.63021 | I10: =I6+I8 -> 734.04118 | J10: =J6+J8 -> 802.45565 | L10: Of course, revenue segment data is a lot harder to find. Dig in the SEC filings or go to the Bloomberg terminals
A11: % change | C11: =(C10-B10)/B10 -> 0.045211373 | D11: =(D10-C10)/C10 -> -0.15909945 | E11: =(E10-D10)/D10 -> 0.096665035 | F11: =(F10-E10)/E10 -> 0.092054959 | G11: =(G10-F10)/F10 -> 0.092340397 | H11: =(H10-G10)/G10 -> 0.092637292 | I11: =(I10-H10)/H10 -> 0.092924603 | J11: =(J10-I10)/I10 -> 0.093202489
A13: COGS | B13: 187.83 | C13: 201.68 | D13: 216.36 | E13: 209.74 | F13: =F10*F14 -> 230.71725 | G13: =G10*G14 -> 252.02177 | H13: =H10*H14 -> 275.36839 | I13: =I10*I14 -> 300.95689 | J13: =J10*J14 -> 329.00682
A14: % revenue | B14: =B13/B10 -> 0.3513468 | C14: =C13/C10 -> 0.36093563 | D14: =D13/D10 -> 0.46046779 | E14: =E13/E10 -> 0.40703293 | F14: 0.41 | G14: =F14 -> 0.41 | H14: =G14 -> 0.41 | I14: =H14 -> 0.41 | J14: =I14 -> 0.41 | L14: Since it's September 2014 when I'm putting this together, two quarters have already passed in 2014. YTD information can help guide annual projections. Use common sense and compare your assumptions against YTD performance.
A16: Gross Profit | B16: =B10-B13 -> 346.77 | C16: =C10-C13 -> 357.09 | D16: =D10-D13 -> 253.51 | E16: =E10-E13 -> 305.55 | F16: =F10-F13 -> 332.00775 | G16: =G10-G13 -> 362.66548 | H16: =H10-H13 -> 396.26183 | I16: =I10-I13 -> 433.0843 | J16: =J10-J13 -> 473.44883
A17: % gross margin | B17: =B16/B10 -> 0.6486532 | C17: =C16/C10 -> 0.63906437 | D17: =D16/D10 -> 0.53953221 | E17: =E16/E10 -> 0.59296707 | F17: =F16/F10 -> 0.59 | G17: =G16/G10 -> 0.59 | H17: =H16/H10 -> 0.59 | I17: =I16/I10 -> 0.59 | J17: =J16/J10 -> 0.59
A19: Sales & Marketing | B19: 120.874 | C19: 124.326 | D19: 127.659 | E19: 127.997 | F19: =F20*F10 -> 140.68125 | G19: =G20*G10 -> 153.67181 | H19: =H20*H10 -> 167.90755 | I19: =I20*I10 -> 183.5103 | J19: =J20*J10 -> 200.61391
A20: % revenue | B20: =B19/B10 -> 0.22610176 | C20: =C19/C10 -> 0.22249942 | D20: =D19/D10 -> 0.27169004 | E20: =E19/E10 -> 0.24839799 | F20: 0.25 | G20: =F20 -> 0.25 | H20: =G20 -> 0.25 | I20: =H20 -> 0.25 | J20: =I20 -> 0.25 | L20: Assumption: they will need to increase marketing to drive advertising revenue to compete with FB and the like
A21: General & Administrative | B21: 85.496 | C21: 91.271 | D21: 97.618 | E21: 93.22 | F21: =F10*F22 -> 90.036 | G21: =G10*G22 -> 98.34996 | H21: =H10*H22 -> 107.46083 | I21: =I10*I22 -> 124.787 | J21: =J10*J22 -> 136.41746
A22: % revenue | B22: =B21/B10 -> 0.15992518 | C22: =C21/C10 -> 0.1633427 | D22: =D21/D10 -> 0.20775534 | E22: =E21/E10 -> 0.18090784 | F22: 0.16 | G22: 0.16 | H22: 0.16 | I22: 0.17 | J22: 0.17
A23: SGA | B23: =SUM(B19,B21) -> 206.37 | C23: =SUM(C19,C21) -> 215.597 | D23: =SUM(D19,D21) -> 225.277 | E23: =SUM(E19,E21) -> 221.217 | F23: =SUM(F19,F21) -> 230.71725 | G23: =SUM(G19,G21) -> 252.02177 | H23: =SUM(H19,H21) -> 275.36839 | I23: =SUM(I19,I21) -> 308.2973 | J23: =SUM(J19,J21) -> 337.03137
A24: % revenue | B24: =B23/B10 -> 0.38602694 | C24: =C23/C10 -> 0.38584212 | D24: =D23/D10 -> 0.47944538 | E24: =E23/E10 -> 0.42930583 | F24: =F23/F10 -> 0.41 | G24: =G23/G10 -> 0.41 | H24: =H23/H10 -> 0.41 | I24: =I23/I10 -> 0.42 | J24: =J23/J10 -> 0.42
A26: R&D | B26: 0 | C26: 0 | D26: 0 | E26: 0 | F26: 0 | G26: 0 | H26: 0 | I26: 0 | J26: 0
A28: D&A | B28: 27.578 | C28: 26.801 | D28: 28.399 | E28: 26.606 | F28: 28 | G28: 28 | H28: 28 | I28: 28 | J28: 28 | L28: Keeping this constant; fairly conservative given past numbers
A29: % revenue | B29: =B28/B10 -> 0.051586233 | C29: =C28/C10 -> 0.047964279 | D29: =D28/D10 -> 0.060440122 | E29: =E28/E10 -> 0.051633061 | F29: =F28/F10 -> 0.049757875 | G29: =G28/G10 -> 0.04555162 | H29: =H28/H10 -> 0.041689608 | I29: =I28/I10 -> 0.038144999 | J29: =J28/J10 -> 0.034892894
A31: EBITDA | B31: =B16-B23 -> 140.4 | C31: =C16-C23 -> 141.493 | D31: =D16-D23 -> 28.233 | E31: =E16-E23 -> 84.333 | F31: =F16-F23 -> 101.2905 | G31: =G16-G23 -> 110.64371 | H31: =H16-H23 -> 120.89344 | I31: =I16-I23 -> 124.787 | J31: =J16-J23 -> 136.41746
A33: EBIT, or Operating Income | B33: =B31-B28 -> 112.822 | C33: =C31-C28 -> 114.692 | D33: =D31-D28 -> -0.166 | E33: =E31-E28 -> 57.727 | F33: =F31-F28 -> 73.2905 | G33: =G31-G28 -> 82.643705 | H33: =H31-H28 -> 92.893438 | I33: =I31-I28 -> 96.787001 | J33: =J31-J28 -> 108.41746
A35: Interest Income | B35: 3.949 | C35: 0.112 | D35: 0.086 | E35: 0.076 | F35: =E35 -> 0.076 | G35: =F35 -> 0.076 | H35: =G35 -> 0.076 | I35: =H35 -> 0.076 | J35: =I35 -> 0.076 | L35: Keeping this constant as an assumption
A36: Interest Expense | B36: 11.453 | C36: 20.645 | D36: 23.334 | E36: 22.826 | F36: =E36 -> 22.826 | G36: =F36 -> 22.826 | H36: =G36 -> 22.826 | I36: =H36 -> 22.826 | J36: =I36 -> 22.826
A37: Net Loss (Gain) from Interest | B37: =-1*(B35-B36) -> 7.504 | C37: =-1*(C35-C36) -> 20.533 | D37: =-1*(D35-D36) -> 23.248 | E37: =-1*(E35-E36) -> 22.75 | F37: =-1*(F35-F36) -> 22.75 | G37: =-1*(G35-G36) -> 22.75 | H37: =-1*(H35-H36) -> 22.75 | I37: =-1*(I35-I36) -> 22.75 | J37: =-1*(J35-J36) -> 22.75
A39: Loss (Gain) on Convertible Notes | B39: 23.332 | C39: 0 | D39: 0 | E39: 4.871 | L39: Struck out all of this because these are unusual expenses difficult to forecast individiually
A40: Gain (Loss) on Investments | B40: 9.517 | C40: -18.516 | D40: -8.074 | E40: 0
A41: Restructuring | B41: 0 | C41: 0 | D41: 7.579 | E41: 0 | L41: "Unusual expenses" are not really common
A42: Transaction, severance, and other expense | B42: 0.072 | C42: 2.328 | D42: 2.297 | E42: 1.353
A43: Unusual Expenses | B43: =SUM(B39:B42) -> 32.921 | C43: =SUM(C39:C42) -> -16.188 | D43: =SUM(D39:D42) -> 1.802 | E43: =SUM(E39:E42) -> 6.224 | F43: 2 | G43: =F43 -> 2 | H43: =G43 -> 2 | I43: =H43 -> 2 | J43: =I43 -> 2 | L43: In general, recurring "unusual expenses" is a red flag for value investors
A45: Earnings Before Taxes (EBT) | B45: =B10-SUM(B13, B23, B28, B37, B43) -> 72.397 | C45: =C10-SUM(C13, C23, C28, C37, C43) -> 110.347 | D45: =D10-SUM(D13, D23, D28, D37, D43) -> -25.216 | E45: =E10-SUM(E13, E23, E28, E37, E43) -> 28.753 | F45: =F10-SUM(F13, F23, F28, F37, F43) -> 48.5405 | G45: =G10-SUM(G13, G23, G28, G37, G43) -> 57.893705 | H45: =H10-SUM(H13, H23, H28, H37, H43) -> 68.143438 | I45: =I10-SUM(I13, I23, I28, I37, I43) -> 72.037001 | J45: =J10-SUM(J13, J23, J28, J37, J43) -> 83.66746
A47: Tax | B47: 20.043 | C47: 46.167 | D47: -2.134 | E47: 13.64 | F47: =IF(F45<0, 0, F48*F31) -> 17.219385 | G47: =IF(G45<0, 0, G48*G31) -> 18.80943 | H47: =IF(H45<0, 0, H48*H31) -> 20.551885 | I47: =IF(I45<0, 0, I48*I31) -> 21.21379 | J47: =IF(J45<0, 0, J48*J31) -> 23.190968
A48: % tax rate | B48: =IF(B45 > 0, B47/B31, 0) -> 0.14275641 | C48: =IF(C45 > 0, C47/C31, 0) -> 0.32628469 | D48: =IF(D45 > 0, D47/D31, 0) -> 0 | E48: =IF(E45 > 0, E47/E31, 0) -> 0.16173977 | F48: 0.17 | G48: 0.17 | H48: 0.17 | I48: 0.17 | J48: 0.17 | L48: Tax rate is zero if earnings are negative
A50: Extraordinary Items | B50: -1.8 | C50: -10.4 | D50: -2.7 | E50: 0 | F50: 0 | G50: 0 | H50: 0 | I50: 0 | J50: 0 | L50: Literally "extraordinary" so don't bother modeling it out unless there's some semblance of a recurring nature. Pretty much here only to reconcile historical income statements
A52: Net Income | B52: =B45-B47-B50 -> 54.154 | C52: =C45-C47-C50 -> 74.58 | D52: =D45-D47-D50 -> -20.382 | E52: =E45-E47-E50 -> 15.113 | F52: =F45-F47-F50 -> 31.321115 | G52: =G45-G47-G50 -> 39.084275 | H52: =H45-H47-H50 -> 47.591554 | I52: =I45-I47 -> 50.823211 | J52: =J45-J47 -> 60.476492

Sheet Working Capital Calculation
A1: Balance Sheet
A2: in $ mms | B2: Historical | F2: Projected
B3: ='Income Statement'!B3 -> 2010 | C3: ='Income Statement'!C3 -> 2011 | D3: ='Income Statement'!D3 -> 2012 | E3: ='Income Statement'!E3 -> 2013 | F3: ='Income Statement'!F3 -> 2014 | G3: ='Income Statement'!G3 -> 2015 | H3: ='Income Statement'!H3 -> 2016 | I3: ='Income Statement'!I3 -> 2017 | J3: ='Income Statement'!J3 -> 2018 | L3: Notes
A5: Accounts Receivable | B5: 134.45 | C5: 121.33 | D5: 106.62 | E5: 124.23 | F5: =AVERAGE(B5:E5) -> 121.6575 | G5: =AVERAGE(C5:F5) -> 118.45937 | H5: =AVERAGE(D5:G5) -> 117.74172 | I5: =AVERAGE(E5:H5) -> 120.52215 | J5: =AVERAGE(F5:I5) -> 119.59519 | L5: Crude approximation through averaging
A6: Inventory | B6: 0 | C6: 0 | D6: 0 | E6: 0 | F6: 0 | G6: 0 | H6: 0 | I6: 0 | J6: 0 | L6: There is no inventory, I'm guessing, because WebMD is a software company and therefore doesn't have actual goods to sell
A7: Accounts Payable | B7: 0 | C7: 0 | D7: 0 | E7: 0 | F7: 0 | G7: 0 | H7: 0 | I7: 0 | J7: 0 | L7: Guess they don't have short-term debt either…
A8: Working Capital | B8: =SUM(B5:B6) - B7 -> 134.45 | C8: =SUM(C5:C6) - C7 -> 121.33 | D8: =SUM(D5:D6) - D7 -> 106.62 | E8: =SUM(E5:E6) - E7 -> 124.23 | F8: =SUM(F5:F6) - F7 -> 121.6575 | G8: =SUM(G5:G6) - G7 -> 118.45937 | H8: =SUM(H5:H6) - H7 -> 117.74172 | I8: =SUM(I5:I6) - I7 -> 120.52215 | J8: =SUM(J5:J6) - J7 -> 119.59519
A10: Change in Working Capital | C10: =B$8-C$8 -> 13.12 | D10: =C$8-D$8 -> 14.71 | E10: =D$8-E$8 -> -17.61 | F10: =E$8-F$8 -> 2.5725 | G10: =F$8-G$8 -> 3.198125 | H10: =G$8-H$8 -> 0.71765625 | I10: =H$8-I$8 -> -2.7804297 | J10: =I$8-J$8 -> 0.92696289 | L10: The working capital calculation is supposed to be non-cash working capital.
L11: which is calculated as AR - AP + Inventory.
L13: Note, this is different from the numbers you'd find on Google or Yahoo Finance
L14: and also different from the general definition of "current assets - current liabilities"
L16: The motivation for this is that we want to use non-cash working capital.

Sheet FCF Calculation
A1: FCF Calculation
A2: in mms | B2: Historical | E2: Projected
B3: ='Income Statement'!C3 -> 2011 | C3: ='Income Statement'!D3 -> 2012 | D3: ='Income Statement'!E3 -> 2013 | E3: ='Income Statement'!F3 -> 2014 | F3: ='Income Statement'!G3 -> 2015 | G3: ='Income Statement'!H3 -> 2016 | H3: ='Income Statement'!I3 -> 2017 | I3: ='Income Statement'!J3 -> 2018 | K3: Notes
A5: Net Income | B5: ='Income Statement'!C52 -> 74.58 | C5: ='Income Statement'!D52 -> -20.382 | D5: ='Income Statement'!E52 -> 15.113 | E5: ='Income Statement'!F52 -> 31.321115 | F5: ='Income Statement'!G52 -> 39.084275 | G5: ='Income Statement'!H52 -> 47.591554 | H5: ='Income Statement'!I52 -> 50.823211 | I5: ='Income Statement'!J52 -> 60.476492
A6: D&A | B6: 26.8 | C6: 280.4 | D6: 26.61 | E6: ='Income Statement'!F28 -> 28 | F6: ='Income Statement'!G28 -> 28 | G6: ='Income Statement'!H28 -> 28 | H6: ='Income Statement'!I28 -> 28 | I6: ='Income Statement'!J28 -> 28 | K6: Naively keeping it constant for now; you'd want to inform these decisions more
A7: Changes in Operating Working Capital | B7: ='Working Capital Calculation'!C10 -> 13.12 | C7: ='Working Capital Calculation'!D10 -> 14.71 | D7: ='Working Capital Calculation'!E10 -> -17.61 | E7: ='Working Capital Calculation'!F10 -> 2.5725 | F7: ='Working Capital Calculation'!G10 -> 3.198125 | G7: ='Working Capital Calculation'!H10 -> 0.71765625 | H7: ='Working Capital Calculation'!I10 -> -2.7804297 | I7: ='Working Capital Calculation'!J10 -> 0.92696289
A8: CapEx | B8: 20.91 | C8: 35.17 | D8: 22.34 | E8: =AVERAGE(B8:D8) -> 26.14 | F8: =AVERAGE(B8:E8) -> 26.14 | G8: =AVERAGE(C8:F8) -> 27.4475 | H8: =AVERAGE(D8:G8) -> 25.516875 | I8: =AVERAGE(E8:H8) -> 26.311094 | K8: Rolling average assumption
A10: FCF | B10: =B5+B6-B7-B8 -> 67.35 | C10: =C5+C6-C7-C8 -> 210.138 | D10: =D5+D6-D7-D8 -> 36.993 | E10: =E5+E6-E7-E8 -> 30.608615 | F10: =F5+F6-F7-F8 -> 37.74615 | G10: =G5+G6-G7-G8 -> 47.426397 | H10: =H5+H6-H7-H8 -> 56.086766 | I10: =I5+I6-I7-I8 -> 61.238435

Sheet FV Calculation
A1: Fair Value Calculation
A2: all numbers in mm's
B3: ='FCF Calculation'!B3 -> 2011 | C3: ='FCF Calculation'!C3 -> 2012 | D3: ='FCF Calculation'!D3 -> 2013 | E3: ='FCF Calculation'!E3 -> 2014 | F3: ='FCF Calculation'!F3 -> 2015 | G3: ='FCF Calculation'!G3 -> 2016 | H3: ='FCF Calculation'!H3 -> 2017 | I3: ='FCF Calculation'!I3 -> 2018 | J3: Terminal
A4: Projected Year | E4: 1 | F4: =E4+1 -> 2 | G4: =F4+1 -> 3 | H4: =G4+1 -> 4 | I4: =H4+1 -> 5 | J4: 5
A5: FCF | B5: ='FCF Calculation'!B10 -> 67.35 | C5: ='FCF Calculation'!C10 -> 210.138 | D5: ='FCF Calculation'!D10 -> 36.993 | E5: ='FCF Calculation'!E10 -> 30.608615 | F5: ='FCF Calculation'!F10 -> 37.74615 | G5: ='FCF Calculation'!G10 -> 47.426397 | H5: ='FCF Calculation'!H10 -> 56.086766 | I5: ='FCF Calculation'!I10 -> 61.238435 | J5: ='FCF Calculation'!I10 -> 61.238435
A6: Discount Factor | E6: =((1+Dashboard!$B$25)^E4) -> 1.0574579 | F6: =((1+Dashboard!$B$25)^F4) -> 1.1182173 | G6: =((1+Dashboard!$B$25)^G4) -> 1.1824678 | H6: =((1+Dashboard!$B$25)^H4) -> 1.2504099 | I6: =((1+Dashboard!$B$25)^I4) -> 1.3222559 | J6: =(Dashboard!$B$25-Dashboard!$B$22) -> 0.037457938
A7: Discounted | E7: =E5/E6 -> 28.945468 | F7: =F5/F6 -> 33.755649 | G7: =G5/G6 -> 40.107984 | H7: =H5/H6 -> 44.854703 | I7: =I5/I6 -> 46.313604 | J7: =(J5*(1+Dashboard!$B$22))/J6 -> 1667.5558
A9: Enterprise Value | B9: =SUM(E7:J7) -> 1861.5333
A10: Net Debt | B10: =952.23 - 781.31 -> 170.92
A11: Fair Value | B11: =B9-B10 -> 1690.6133
A13: WACC Assumptions
A15: WACC | B15: =C18*B24+ C19*B29 -> 0.057457938
B17: Amount | C17: Weight | E17: Notes
A18: Equity | B18: 148.47 | C18: =B18/(SUM($B$18:$B$19)) -> 0.13488689
A19: Debt | B19: 952.23 | C19: =B19/(SUM($B$18:$B$19)) -> 0.86511311
A22: Beta | B22: 0.82 | E22: (Yahoo! Finance), although you should try calculating it yourself
A23: Rm-Rf | B23: =Dashboard!B23-Dashboard!B24 -> 0.037
A24: Cost of Equity | B24: =Dashboard!B24+B22*B23 -> 0.05334
A27: Cost of Debt | B27: 0.07
A28: Tax Rate | B28: ='Income Statement'!F48 -> 0.17
A29: After Tax Cost of Debt | B29: =B27*(1-B28) -> 0.0581
A32: Shares Outstanding | B32: 38.38
