Workbook

Sheet Sales report
B2: Monthly Sales Report
B3: Date | C3: Day | D3: Product | E3: Quantity | F3: Sales channel | G3: Cost Price | H3: Sell Price | I3: Profit | J3: Margin | K3: Net income | L3: Revenue
B4: 43009 | C4: =TEXT(B4,"dddd") -> Sunday | D4: A | E4: 25 | F4: Amazon | G4: =IF(D4="","",VLOOKUP(D4,'Product Sheet'!$B$3:$D$7,2,FALSE)) -> 10 | H4: =IF(D4="","",VLOOKUP(D4,'Product Sheet'!$B$3:$D$7,3,FALSE)) -> 15 | I4: =H4-G4 -> 5 | J4: =I4/H4 -> 0.33333333 | K4: =I4*E4 -> 125 | L4: =H4*E4 -> 375
B5: 43009 | C5: =TEXT(B5,"dddd") -> Sunday | D5: A | E5: 10 | F5: Website | G5: =IF(D5="","",VLOOKUP(D5,'Product Sheet'!$B$3:$D$7,2,FALSE)) -> 10 | H5: =IF(D5="","",VLOOKUP(D5,'Product Sheet'!$B$3:$D$7,3,FALSE)) -> 15 | I5: =H5-G5 -> 5 | J5: =I5/H5 -> 0.33333333 | K5: =I5*E5 -> 50 | L5: =H5*E5 -> 150
B6: 43009 | C6: =TEXT(B6,"dddd") -> Sunday | D6: E | E6: 50 | F6: Amazon | G6: =IF(D6="","",VLOOKUP(D6,'Product Sheet'!$B$3:$D$7,2,FALSE)) -> 8 | H6: =IF(D6="","",VLOOKUP(D6,'Product Sheet'!$B$3:$D$7,3,FALSE)) -> 10 | I6: =H6-G6 -> 2 | J6: =I6/H6 -> 0.2 | K6: =I6*E6 -> 100 | L6: =H6*E6 -> 500
B7: 43010 | C7: =TEXT(B7,"dddd") -> Monday | D7: B | E7: 25 | F7: Big basket | G7: =IF(D7="","",VLOOKUP(D7,'Product Sheet'!$B$3:$D$7,2,FALSE)) -> 5 | H7: =IF(D7="","",VLOOKUP(D7,'Product Sheet'!$B$3:$D$7,3,FALSE)) -> 10 | I7: =H7-G7 -> 5 | J7: =I7/H7 -> 0.5 | K7: =I7*E7 -> 125 | L7: =H7*E7 -> 250
B8: 43010 | C8: =TEXT(B8,"dddd") -> Monday | D8: C | E8: 25 | F8: Website | G8: =IF(D8="","",VLOOKUP(D8,'Product Sheet'!$B$3:$D$7,2,FALSE)) -> 12 | H8: =IF(D8="","",VLOOKUP(D8,'Product Sheet'!$B$3:$D$7,3,FALSE)) -> 20 | I8: =H8-G8 -> 8 | J8: =I8/H8 -> 0.4 | K8: =I8*E8 -> 200 | L8: =H8*E8 -> 500
B9: 43012 | C9: =TEXT(B9,"dddd") -> Wednesday | D9: E | E9: 10 | F9: Amazon | G9: =IF(D9="","",VLOOKUP(D9,'Product Sheet'!$B$3:$D$7,2,FALSE)) -> 8 | H9: =IF(D9="","",VLOOKUP(D9,'Product Sheet'!$B$3:$D$7,3,FALSE)) -> 10 | I9: =H9-G9 -> 2 | J9: =I9/H9 -> 0.2 | K9: =I9*E9 -> 20 | L9: =H9*E9 -> 100
B10: 43012 | C10: =TEXT(B10,"dddd") -> Wednesday | D10: D | E10: 20 | F10: Flipkart | G10: =IF(D10="","",VLOOKUP(D10,'Product Sheet'!$B$3:$D$7,2,FALSE)) -> 20 | H10: =IF(D10="","",VLOOKUP(D10,'Product Sheet'!$B$3:$D$7,3,FALSE)) -> 30 | I10: =H10-G10 -> 10 | J10: =I10/H10 -> 0.33333333 | K10: =I10*E10 -> 200 | L10: =H10*E10 -> 600
B11: 43013 | C11: =TEXT(B11,"dddd") -> Thursday | D11: C | E11: 40 | F11: Amazon | G11: =IF(D11="","",VLOOKUP(D11,'Product Sheet'!$B$3:$D$7,2,FALSE)) -> 12 | H11: =IF(D11="","",VLOOKUP(D11,'Product Sheet'!$B$3:$D$7,3,FALSE)) -> 20 | I11: =H11-G11 -> 8 | J11: =I11/H11 -> 0.4 | K11: =I11*E11 -> 320 | L11: =H11*E11 -> 800
B12: 43013 | C12: =TEXT(B12,"dddd") -> Thursday | D12: D | E12: 50 | F12: Flipkart | G12: =IF(D12="","",VLOOKUP(D12,'Product Sheet'!$B$3:$D$7,2,FALSE)) -> 20 | H12: =IF(D12="","",VLOOKUP(D12,'Product Sheet'!$B$3:$D$7,3,FALSE)) -> 30 | I12: =H12-G12 -> 10 | J12: =I12/H12 -> 0.33333333 | K12: =I12*E12 -> 500 | L12: =H12*E12 -> 1500
B13: 43014 | C13: =TEXT(B13,"dddd") -> Friday | D13: E | E13: 100 | F13: Flipkart | G13: =IF(D13="","",VLOOKUP(D13,'Product Sheet'!$B$3:$D$7,2,FALSE)) -> 8 | H13: =IF(D13="","",VLOOKUP(D13,'Product Sheet'!$B$3:$D$7,3,FALSE)) -> 10 | I13: =H13-G13 -> 2 | J13: =I13/H13 -> 0.2 | K13: =I13*E13 -> 200 | L13: =H13*E13 -> 1000
B14: 43015 | C14: =TEXT(B14,"dddd") -> Saturday | D14: D | E14: 25 | F14: Big basket | G14: =IF(D14="","",VLOOKUP(D14,'Product Sheet'!$B$3:$D$7,2,FALSE)) -> 20 | H14: =IF(D14="","",VLOOKUP(D14,'Product Sheet'!$B$3:$D$7,3,FALSE)) -> 30 | I14: =H14-G14 -> 10 | J14: =I14/H14 -> 0.33333333 | K14: =I14*E14 -> 250 | L14: =H14*E14 -> 750
B15: 43016 | C15: =TEXT(B15,"dddd") -> Sunday | D15: A | E15: 40 | F15: Big basket | G15: =IF(D15="","",VLOOKUP(D15,'Product Sheet'!$B$3:$D$7,2,FALSE)) -> 10 | H15: =IF(D15="","",VLOOKUP(D15,'Product Sheet'!$B$3:$D$7,3,FALSE)) -> 15 | I15: =H15-G15 -> 5 | J15: =I15/H15 -> 0.33333333 | K15: =I15*E15 -> 200 | L15: =H15*E15 -> 600
... B31: 43038 | C31: =TEXT(B31,"dddd") -> Monday | D31: D | E31: 20 | F31: Amazon | G31: =IF(D31="","",VLOOKUP(D31,'Product Sheet'!$B$3:$D$7,2,FALSE)) -> 20 | H31: =IF(D31="","",VLOOKUP(D31,'Product Sheet'!$B$3:$D$7,3,FALSE)) -> 30 | I31: =H31-G31 -> 10 | J31: =I31/H31 -> 0.33333333 | K31: =I31*E31 -> 200 | L31: =H31*E31 -> 600

Sheet Product Sheet
B2: Product Name | C2: Cost Price | D2: Sales Price | E2: Sales channel
B3: A | C3: 10 | D3: 15 | E3: Amazon
B4: B | C4: 5 | D4: 10 | E4: Website
B5: C | C5: 12 | D5: 20 | E5: Big basket
B6: D | C6: 20 | D6: 30 | E6: Flipkart
B7: E | C7: 8 | D7: 10 | E7: Shopclues
C49: Product
C50: A
C51: B
C52: C
C53: D
C54: E

Sheet Online Sales Tracker
B2: www.ExcelDataPro.com
B3: Online Sales Tracker
B4: Sales Summary
B5: Volume Breakup
B6: Product | C6: Website | D6: Amazon | E6: Big basket | F6: Flipkart | G6: Shopclues | H6: Volume
B7: ='Product Sheet'!B3 -> A | C7: =SUMIFS('Sales report'!$E$4:E$31,'Sales report'!$D$4:$D$31,B7,'Sales report'!$F$4:$F$31,C6) -> 10 | D7: =SUMIFS('Sales report'!$E$4:$E$31,'Sales report'!$D$4:$D$31,B7,'Sales report'!$F$4:$F$31,D6) -> 25 | E7: =SUMIFS('Sales report'!$E$4:$E$31,'Sales report'!$D$4:$D$31,B7,'Sales report'!$F$4:$F$31,E6) -> 40 | F7: =SUMIFS('Sales report'!$E$4:$E$31,'Sales report'!$D$4:$D$31,B7,'Sales report'!$F$4:$F$31,F6) -> 0 | G7: =SUMIFS('Sales report'!$E$4:$E$31,'Sales report'!$D$4:$D$31,B7,'Sales report'!$F$4:$F$31,G6) -> 50 | H7: =C7+D7+E7+F7+G7 -> 125
B8: ='Product Sheet'!B4 -> B | C8: =SUMIFS('Sales report'!$E$4:$E$31,'Sales report'!$D$4:$D$31,B8,'Sales report'!$F$4:$F$31,C6) -> 20 | D8: =SUMIFS('Sales report'!$E$4:$E$31,'Sales report'!$D$4:$D$31,B8,'Sales report'!$F$4:$F$31,D6) -> 60 | E8: =SUMIFS('Sales report'!$E$4:$E$31,'Sales report'!$D$4:$D$31,B8,'Sales report'!$F$4:$F$31,E6) -> 115 | F8: =SUMIFS('Sales report'!$E$4:$E$31,'Sales report'!$D$4:$D$31,B8,'Sales report'!$F$4:$F$31,F6) -> 50 | G8: =SUMIFS('Sales report'!$E$4:$E$31,'Sales report'!$D$4:$D$31,B8,'Sales report'!$F$4:$F$31,G6) -> 50 | H8: =C8+D8+E8+F8+G8 -> 295
B9: ='Product Sheet'!B5 -> C | C9: =SUMIFS('Sales report'!$E$4:$E$31,'Sales report'!$D$4:$D$31,B9,'Sales report'!$F$4:$F$31,C6) -> 80 | D9: =SUMIFS('Sales report'!$E$4:$E$31,'Sales report'!$D$4:$D$31,B9,'Sales report'!$F$4:$F$31,D6) -> 40 | E9: =SUMIFS('Sales report'!$E$4:$E$31,'Sales report'!$D$4:$D$31,B9,'Sales report'!$F$4:$F$31,E6) -> 0 | F9: =SUMIFS('Sales report'!$E$4:$E$31,'Sales report'!$D$4:$D$31,B9,'Sales report'!$F$4:$F$31,F6) -> 40 | G9: =SUMIFS('Sales report'!$E$4:$E$31,'Sales report'!$D$4:$D$31,B9,'Sales report'!$F$4:$F$31,G6) -> 100 | H9: =C9+D9+E9+F9+G9 -> 260
B10: ='Product Sheet'!B6 -> D | C10: =SUMIFS('Sales report'!$E$4:$E$31,'Sales report'!$D$4:$D$31,B10,'Sales report'!$F$4:$F$31,C6) -> 45 | D10: =SUMIFS('Sales report'!$E$4:$E$31,'Sales report'!$D$4:$D$31,B10,'Sales report'!$F$4:$F$31,D6) -> 20 | E10: =SUMIFS('Sales report'!$E$4:$E$31,'Sales report'!$D$4:$D$31,B10,'Sales report'!$F$4:$F$31,E6) -> 25 | F10: =SUMIFS('Sales report'!$E$4:$E$31,'Sales report'!$D$4:$D$31,B10,'Sales report'!$F$4:$F$31,F6) -> 70 | G10: =SUMIFS('Sales report'!$E$4:$E$31,'Sales report'!$D$4:$D$31,B10,'Sales report'!$F$4:$F$31,G6) -> 25 | H10: =C10+D10+E10+F10+G10 -> 185
B11: ='Product Sheet'!B7 -> E | C11: =SUMIFS('Sales report'!$E$4:$E$31,'Sales report'!$D$4:$D$31,B11,'Sales report'!$F$4:$F$31,C6) -> 0 | D11: =SUMIFS('Sales report'!$E$4:$E$31,'Sales report'!$D$4:$D$31,B11,'Sales report'!$F$4:$F$31,D6) -> 60 | E11: =SUMIFS('Sales report'!$E$4:$E$31,'Sales report'!$D$4:$D$31,B11,'Sales report'!$F$4:$F$31,E6) -> 0 | F11: =SUMIFS('Sales report'!$E$4:$E$31,'Sales report'!$D$4:$D$31,B11,'Sales report'!$F$4:$F$31,F6) -> 200 | G11: =SUMIFS('Sales report'!$E$4:$E$31,'Sales report'!$D$4:$D$31,B11,'Sales report'!$F$4:$F$31,G6) -> 0 | H11: =C11+D11+E11+F11+G11 -> 260
B12: TOTAL | C12: =SUM(C7:C11) -> 155 | D12: =SUM(D7:D11) -> 205 | E12: =SUM(E7:E11) -> 180 | F12: =SUM(F7:F11) -> 360 | G12: =SUM(G7:G11) -> 225 | H12: =SUM(H7:H11) -> 1125
B13: Product-wise Profit Breakup
B14: Product | C14: Website | D14: Amazon | E14: Big Basket | F14: Flipkart | G14: Shopclues | H14: Profit
B15: A | C15: =SUMIFS('Sales report'!$K$4:$K$31,'Sales report'!$D$4:$D$31,B15,'Sales report'!$F$4:$F$31,C14) -> 50 | D15: =SUMIFS('Sales report'!$K$4:$K$31,'Sales report'!$D$4:$D$31,B15,'Sales report'!$F$4:$F$31,D6) -> 125 | E15: =SUMIFS('Sales report'!$K$4:$K$31,'Sales report'!$D$4:$D$31,B15,'Sales report'!$F$4:$F$31,E6) -> 200 | F15: =SUMIFS('Sales report'!$K$4:$K$31,'Sales report'!$D$4:$D$31,B15,'Sales report'!$F$4:$F$31,F6) -> 0 | G15: =SUMIFS('Sales report'!$K$4:$K$31,'Sales report'!$D$4:$D$31,B15,'Sales report'!$F$4:$F$31,G6) -> 250 | H15: =C15+D15+ E15+F15+G15 -> 625
B16: B | C16: =SUMIFS('Sales report'!$K$4:$K$31,'Sales report'!$D$4:$D$31,B16,'Sales report'!$F$4:$F$31,C14) -> 100 | D16: =SUMIFS('Sales report'!$K$4:$K$31,'Sales report'!$D$4:$D$31,B16,'Sales report'!$F$4:$F$31,D6) -> 300 | E16: =SUMIFS('Sales report'!$K$4:$K$31,'Sales report'!$D$4:$D$31,B16,'Sales report'!$F$4:$F$31,E6) -> 575 | F16: =SUMIFS('Sales report'!$K$4:$K$31,'Sales report'!$D$4:$D$31,B16,'Sales report'!$F$4:$F$31,F6) -> 250 | G16: =SUMIFS('Sales report'!$K$4:$K$31,'Sales report'!$D$4:$D$31,B16,'Sales report'!$F$4:$F$31,G6) -> 250 | H16: =C16+D16+ E16+F16+G16 -> 1475
B17: C | C17: =SUMIFS('Sales report'!$K$4:$K$31,'Sales report'!$D$4:$D$31,B17,'Sales report'!$F$4:$F$31,C14) -> 640 | D17: =SUMIFS('Sales report'!$K$4:$K$31,'Sales report'!$D$4:$D$31,B17,'Sales report'!$F$4:$F$31,D6) -> 320 | E17: =SUMIFS('Sales report'!$K$4:$K$31,'Sales report'!$D$4:$D$31,B17,'Sales report'!$F$4:$F$31,E6) -> 0 | F17: =SUMIFS('Sales report'!$K$4:$K$31,'Sales report'!$D$4:$D$31,B17,'Sales report'!$F$4:$F$31,F6) -> 320 | G17: =SUMIFS('Sales report'!$K$4:$K$31,'Sales report'!$D$4:$D$31,B17,'Sales report'!$F$4:$F$31,G6) -> 800 | H17: =C17+D17+ E17+F17+G17 -> 2080
B18: D | C18: =SUMIFS('Sales report'!$K$4:$K$31,'Sales report'!$D$4:$D$31,B18,'Sales report'!$F$4:$F$31,C14) -> 450 | D18: =SUMIFS('Sales report'!$K$4:$K$31,'Sales report'!$D$4:$D$31,B18,'Sales report'!$F$4:$F$31,D6) -> 200 | E18: =SUMIFS('Sales report'!$K$4:$K$31,'Sales report'!$D$4:$D$31,B18,'Sales report'!$F$4:$F$31,E6) -> 250 | F18: =SUMIFS('Sales report'!$K$4:$K$31,'Sales report'!$D$4:$D$31,B18,'Sales report'!$F$4:$F$31,F6) -> 700 | G18: =SUMIFS('Sales report'!$K$4:$K$31,'Sales report'!$D$4:$D$31,B18,'Sales report'!$F$4:$F$31,G6) -> 250 | H18: =C18+D18+ E18+F18+G18 -> 1850
B19: E | C19: =SUMIFS('Sales report'!$K$4:$K$31,'Sales report'!$D$4:$D$31,B19,'Sales report'!$F$4:$F$31,C14) -> 0 | D19: =SUMIFS('Sales report'!$K$4:$K$31,'Sales report'!$D$4:$D$31,B19,'Sales report'!$F$4:$F$31,D6) -> 120 | E19: =SUMIFS('Sales report'!$K$4:$K$31,'Sales report'!$D$4:$D$31,B19,'Sales report'!$F$4:$F$31,E6) -> 0 | F19: =SUMIFS('Sales report'!$K$4:$K$31,'Sales report'!$D$4:$D$31,B19,'Sales report'!$F$4:$F$31,F6) -> 400 | G19: =SUMIFS('Sales report'!$K$4:$K$31,'Sales report'!$D$4:$D$31,B19,'Sales report'!$F$4:$F$31,G6) -> 0 | H19: =C19+D19+ E19+F19+G19 -> 520
